{
  "fonte": "Power Automate",
  "atualizado": "aguardando",
  "contratos": [
    {
      "id": "10",
      "uen": "136",
      "diretoria": "RD",
      "cliente": "COELBA",
      "contrato": "4600033089 - UEN 136",
      "contratoCliente": "4600033089",
      "linhaNegocios": "CCM/STC",
      "mesReajuste": "Setembro",
      "clausula": "14.3",
      "obs": "",
      "tipoContratacao": "Contrato Contínuo",
      "valorTotal": 125170498.98,
      "dataInicio": "2014-09-01",
      "dataTerminoAdtv": "2026-06-30",
      "vigenciaMeses": "141",
      "status": "ok",
      "indiceSugerido": "ipca_12m",
      "reajuste": "IPCA"
    },
    {
      "id": "38",
      "uen": "186, 187, 188,190",
      "diretoria": "RD",
      "cliente": "ENERGISA MS",
      "contrato": "2020.0101.01/2020.01",
      "contratoCliente": "2020.0101.01/2020.0102.01\nWS 70924",
      "linhaNegocios": "CCM/STC",
      "mesReajuste": "Novembro",
      "clausula": "TAC02",
      "obs": "Conforme TAC04",
      "tipoContratacao": "Contrato Contínuo",
      "valorTotal": 164989060.22,
      "dataInicio": "2020-05-01",
      "dataTerminoAdtv": "2026-07-31",
      "vigenciaMeses": "74",
      "status": "ok",
      "indiceSugerido": "",
      "reajuste": "P = PO + PO x (40% x MO + 10% x ME + 5% x CO + 45% x IPCA).\n\nPO = Preço data base – Data base: 01/11/2019\nMO = Mão de obra – INCC – DI = código 160906, FGV;\nME =  Índice de Bens de Produção, Máquinas e Equipamentos - Coluna 15 - FGV\nCO = Combustível e lubrificantes = Índice de variação de bens intermediários - combustíveis e lubrificantes para produção, da FGV, código 1004820.\nIPCA = Índice Nacional de Preços ao Consumidor Amplo."
    },
    {
      "id": "71",
      "uen": "813",
      "diretoria": "GT",
      "cliente": "AES TIETÊ",
      "contrato": "4600001984 - UEN 813",
      "contratoCliente": "4600001984",
      "linhaNegocios": "O&M",
      "mesReajuste": "Março",
      "clausula": "V - 3º",
      "obs": "",
      "tipoContratacao": "Contrato Contínuo",
      "valorTotal": 5518831.65,
      "dataInicio": "2021-03-22",
      "dataTerminoAdtv": "2026-03-22",
      "vigenciaMeses": "60",
      "status": "vence",
      "indiceSugerido": "",
      "reajuste": ""
    },
    {
      "id": "74",
      "uen": "110, 111, 112, 121, 122, 123, 125, 126, 127",
      "diretoria": "RD",
      "cliente": "EDP ES",
      "contrato": "0002/2021",
      "contratoCliente": "0002/2021; 4600027185; 4600027205; 4600027207",
      "linhaNegocios": "CCM/STC",
      "mesReajuste": "Junho",
      "clausula": "TAC 01",
      "obs": "Conforme TAC01",
      "tipoContratacao": "Contrato Contínuo",
      "valorTotal": 288681494.91,
      "dataInicio": "2021-06-01",
      "dataTerminoAdtv": "2026-06-30",
      "vigenciaMeses": "60",
      "status": "ok",
      "indiceSugerido": "ipca_12m",
      "reajuste": "IPCA"
    },
    {
      "id": "75",
      "uen": "635",
      "diretoria": "GT",
      "cliente": "EDP ES",
      "contrato": "4600027342 - UEN 635",
      "contratoCliente": "4600027342",
      "linhaNegocios": "MANUTENÇÃO",
      "mesReajuste": "Junho",
      "clausula": "4.4",
      "obs": "",
      "tipoContratacao": "Contrato Contínuo",
      "valorTotal": 19073141.57,
      "dataInicio": "2021-06-22",
      "dataTerminoAdtv": "2026-06-30",
      "vigenciaMeses": "60",
      "status": "ok",
      "indiceSugerido": "",
      "reajuste": ""
    },
    {
      "id": "77",
      "uen": "822",
      "diretoria": "GT",
      "cliente": "RENOVA",
      "contrato": "OMEOL201600017",
      "contratoCliente": "OMEOL201600017",
      "linhaNegocios": "O&M",
      "mesReajuste": "Outubro",
      "clausula": "TAC01 - 11.1.4",
      "obs": "Conforme TAC01",
      "tipoContratacao": "Contrato Contínuo",
      "valorTotal": 20899620.0,
      "dataInicio": "2021-10-01",
      "dataTerminoAdtv": "2026-10-01",
      "vigenciaMeses": "60",
      "status": "ok",
      "indiceSugerido": "",
      "reajuste": ""
    },
    {
      "id": "79",
      "uen": "202",
      "diretoria": "RD",
      "cliente": "CEMIG",
      "contrato": "4680006675 - UEN 202",
      "contratoCliente": "4680006675",
      "linhaNegocios": "STC",
      "mesReajuste": "Agosto",
      "clausula": "6",
      "obs": "Quem faz a solicitação é a REMO",
      "tipoContratacao": "Contrato Contínuo",
      "valorTotal": 120371794.55,
      "dataInicio": "2022-07-01",
      "dataTerminoAdtv": "2027-07-01",
      "vigenciaMeses": "60",
      "status": "ok",
      "indiceSugerido": "",
      "reajuste": ""
    },
    {
      "id": "86",
      "uen": "620",
      "diretoria": "GT",
      "cliente": "BRASKEM",
      "contrato": "4800004599 - UEN 620",
      "contratoCliente": "4800004599",
      "linhaNegocios": "MANUTENÇÃO",
      "mesReajuste": "Maio",
      "clausula": "F.2.2",
      "obs": "",
      "tipoContratacao": "Contrato Contínuo",
      "valorTotal": 21739303.66,
      "dataInicio": "2022-05-01",
      "dataTerminoAdtv": "2028-05-01",
      "vigenciaMeses": "72",
      "status": "ok",
      "indiceSugerido": "ipca_12m",
      "reajuste": "IPCA"
    },
    {
      "id": "87",
      "uen": "811",
      "diretoria": "GT",
      "cliente": "SAMARCO",
      "contrato": "4600003379 - UEN 811",
      "contratoCliente": "4600003379",
      "linhaNegocios": "O&M",
      "mesReajuste": "Maio",
      "clausula": "9",
      "obs": "",
      "tipoContratacao": "Contrato Contínuo",
      "valorTotal": 58054501.28,
      "dataInicio": "2022-07-01",
      "dataTerminoAdtv": "2026-06-30",
      "vigenciaMeses": "47",
      "status": "ok",
      "indiceSugerido": "",
      "reajuste": ""
    },
    {
      "id": "89",
      "uen": "203",
      "diretoria": "RD",
      "cliente": "CEMIG",
      "contrato": "4680006646 - UEN 203",
      "contratoCliente": "4680006646",
      "linhaNegocios": "CCM",
      "mesReajuste": "Maio",
      "clausula": "6",
      "obs": "Solicitar dia 16/04",
      "tipoContratacao": "Contrato Contínuo",
      "valorTotal": 113834000.0,
      "dataInicio": "2022-08-05",
      "dataTerminoAdtv": "2027-08-04",
      "vigenciaMeses": "59",
      "status": "ok",
      "indiceSugerido": "ipca_12m",
      "reajuste": "IPCA"
    },
    {
      "id": "90",
      "uen": "615",
      "diretoria": "RD",
      "cliente": "LIGHT",
      "contrato": "46000009066 -UEN 615",
      "contratoCliente": "4600009066",
      "linhaNegocios": "MANUTENÇÃO",
      "mesReajuste": "Junho",
      "clausula": "12",
      "obs": "Se não solicitar no prazo, não consegue retroativo",
      "tipoContratacao": "Contrato Contínuo",
      "valorTotal": 5798315.95,
      "dataInicio": "2022-06-03",
      "dataTerminoAdtv": "2026-04-30",
      "vigenciaMeses": "46",
      "status": "vence",
      "indiceSugerido": "ipca_12m",
      "reajuste": "IPCA"
    },
    {
      "id": "91",
      "uen": "661",
      "diretoria": "GT",
      "cliente": "EDP T",
      "contrato": "4600029508 - UEN 661",
      "contratoCliente": "4600029508",
      "linhaNegocios": "MANUTENÇÃO",
      "mesReajuste": "Julho",
      "clausula": "5.1",
      "obs": "",
      "tipoContratacao": "Contrato Contínuo",
      "valorTotal": 2612650.0,
      "dataInicio": "2022-09-04",
      "dataTerminoAdtv": "2026-03-12",
      "vigenciaMeses": "42",
      "status": "vence",
      "indiceSugerido": "ipca_12m",
      "reajuste": "IPCA"
    },
    {
      "id": "92",
      "uen": "660",
      "diretoria": "GT",
      "cliente": "EDP T",
      "contrato": "4600029518 - UEN 660",
      "contratoCliente": "4600029518",
      "linhaNegocios": "MANUTENÇÃO",
      "mesReajuste": "Julho",
      "clausula": "5.1",
      "obs": "",
      "tipoContratacao": "Contrato Contínuo",
      "valorTotal": 8639816.7,
      "dataInicio": "2022-08-31",
      "dataTerminoAdtv": "2026-05-31",
      "vigenciaMeses": "45",
      "status": "ok",
      "indiceSugerido": "ipca_12m",
      "reajuste": "IPCA"
    },
    {
      "id": "93",
      "uen": "620",
      "diretoria": "GT",
      "cliente": "KINROSS",
      "contrato": "SPOT",
      "contratoCliente": "133268-B2",
      "linhaNegocios": "MANUTENÇÃO",
      "mesReajuste": "Janeiro",
      "clausula": "5",
      "obs": "",
      "tipoContratacao": "Contrato Contínuo",
      "valorTotal": 1500000.0,
      "dataInicio": "2021-05-24",
      "dataTerminoAdtv": "2026-04-30",
      "vigenciaMeses": "59",
      "status": "vence",
      "indiceSugerido": "",
      "reajuste": ""
    },
    {
      "id": "98",
      "uen": "620",
      "diretoria": "GT",
      "cliente": "MINERAÇÃO MARACÁ",
      "contrato": "9830 - UEN 620",
      "contratoCliente": "9830",
      "linhaNegocios": "MANUTENÇÃO",
      "mesReajuste": "Março",
      "clausula": "VIII",
      "obs": "",
      "tipoContratacao": "Contrato Contínuo",
      "valorTotal": 882822.5,
      "dataInicio": "2023-03-27",
      "dataTerminoAdtv": "2026-03-26",
      "vigenciaMeses": "35",
      "status": "vence",
      "indiceSugerido": "",
      "reajuste": ""
    },
    {
      "id": "102",
      "uen": "825",
      "diretoria": "GT",
      "cliente": "ALIANÇA",
      "contrato": "84895 - UEN 825",
      "contratoCliente": "84895",
      "linhaNegocios": "O&M",
      "mesReajuste": "Maio",
      "clausula": "14.4.1",
      "obs": "",
      "tipoContratacao": "Contrato Contínuo",
      "valorTotal": 8815920.0,
      "dataInicio": "2023-07-28",
      "dataTerminoAdtv": "2028-07-28",
      "vigenciaMeses": "60",
      "status": "ok",
      "indiceSugerido": "",
      "reajuste": ""
    },
    {
      "id": "104",
      "uen": "176",
      "diretoria": "RD",
      "cliente": "CPFL",
      "contrato": "CW2326043 - UEN 176",
      "contratoCliente": "CW2326043",
      "linhaNegocios": "LEITURA",
      "mesReajuste": "Janeiro",
      "clausula": "6.2",
      "obs": "Primeiro Reaj. Em Janeiro",
      "tipoContratacao": "Contrato Contínuo",
      "valorTotal": 41330807.34,
      "dataInicio": "2024-01-01",
      "dataTerminoAdtv": "2028-01-01",
      "vigenciaMeses": "48",
      "status": "ok",
      "indiceSugerido": "",
      "reajuste": "PR = Po. [0,62. (MO) + 0,18 (BM) + 0,10  (PI27i/PI27o) + 0,10 (IPCi/0PCo)] \nPr = Preço reajustado;  \nPo = Preço inicial do contrato;  \nMO = Índice para Mão-de-Obra de Leitura e Entrega (Último Acordo Coletivo da Categoria);  \nBM = Variação média dos benefícios de Leitura e Entrega (Cesta básica, vale- refeição, PLR) entre o \núltimo Acordo coletivo da Categoria e o seu respectivo anterior. PI27 = Produtos Industrializados;  \nIPC (FIPE) = Índice de Preços ao Consumidor para cálculo da variação dos custos administrativos.  \ni = Índices básicos referentes ao 1º mês anterior a data do reajuste.\no = índices básicos referentes ao 1º mês anterior a data da assinatura do contrato, ou do último \nreajuste aplicado.  \nIo = índices básicos referentes ao 1º mês anterior à data base;  \nIi = índices básicos referentes ao 1º mês anterior à data do reajuste.  \nPreço base = é o preço da base econômica da proposta que é abril/2023;"
    },
    {
      "id": "105",
      "uen": "177",
      "diretoria": "RD",
      "cliente": "CPFL",
      "contrato": "CW2326040 - UEN 177",
      "contratoCliente": "CW2326040",
      "linhaNegocios": "LEITURA",
      "mesReajuste": "Janeiro",
      "clausula": "6.2",
      "obs": "Primeiro Reaj. Em Janeiro",
      "tipoContratacao": "Contrato Contínuo",
      "valorTotal": 33273307.55,
      "dataInicio": "2024-01-01",
      "dataTerminoAdtv": "2028-01-01",
      "vigenciaMeses": "48",
      "status": "ok",
      "indiceSugerido": "",
      "reajuste": "PR = Po. [0,62. (MO) + 0,18 (BM) + 0,10  (PI27i/PI27o) + 0,10 (IPCi/0PCo)] \nPr = Preço reajustado;  \nPo = Preço inicial do contrato;  \nMO = Índice para Mão-de-Obra de Leitura e Entrega (Último Acordo Coletivo da Categoria);  \nBM = Variação média dos benefícios de Leitura e Entrega (Cesta básica, vale- refeição, PLR) entre o \núltimo Acordo coletivo da Categoria e o seu respectivo anterior. PI27 = Produtos Industrializados;  \nIPC (FIPE) = Índice de Preços ao Consumidor para cálculo da variação dos custos administrativos.  \ni = Índices básicos referentes ao 1º mês anterior a data do reajuste.\no = índices básicos referentes ao 1º mês anterior a data da assinatura do contrato, ou do último \nreajuste aplicado.  \nIo = índices básicos referentes ao 1º mês anterior à data base;  \nIi = índices básicos referentes ao 1º mês anterior à data do reajuste.  \nPreço base = é o preço da base econômica da proposta que é abril/2023;"
    },
    {
      "id": "106",
      "uen": "175",
      "diretoria": "RD",
      "cliente": "CPFL",
      "contrato": "CW2325894 - UEN 175",
      "contratoCliente": "CW2325894",
      "linhaNegocios": "LEITURA",
      "mesReajuste": "Janeiro",
      "clausula": "6.2",
      "obs": "Primeiro Reaj. Em Janeiro",
      "tipoContratacao": "Contrato Contínuo",
      "valorTotal": 50701411.28,
      "dataInicio": "2023-11-01",
      "dataTerminoAdtv": "2027-11-01",
      "vigenciaMeses": "48",
      "status": "ok",
      "indiceSugerido": "",
      "reajuste": ""
    },
    {
      "id": "109",
      "uen": "191",
      "diretoria": "RD",
      "cliente": "ENERGISA MS",
      "contrato": "WS99093 - UEN 191",
      "contratoCliente": "WS 99093",
      "linhaNegocios": "STC",
      "mesReajuste": "Outubro",
      "clausula": "reajuste",
      "obs": "Página 2",
      "tipoContratacao": "Contrato Contínuo",
      "valorTotal": 16364448.0,
      "dataInicio": "2024-01-01",
      "dataTerminoAdtv": "2027-12-31",
      "vigenciaMeses": "47",
      "status": "ok",
      "indiceSugerido": "",
      "reajuste": "P = PO + PO x (40% x MO + 10% x ME + 5% x DI + 45% x IPCA).\n\nPO = Preço data base – Data base: assinatura do contrato;\nMO = Mão de obra – INCC – DI = código 160906, FGV;\nME = IPA-EP-DI Máquinas, aparelhos e equipamentos – código 1416650, FGV\nDI = Diesel S-10 = Variação preço médio revenda, Centro Oeste, ANP (https://www.gov.br/anp/pt-br/assuntos/precos-e-defesa-da-concorrencia/precos/precos-revenda-e-de-distribuicao-combustiveis/serie-historica-do-levantamento-de-precos);\nIPCA = Índice Nacional de Preços ao Consumidor Amplo."
    },
    {
      "id": "110",
      "uen": "192, 193, 194, 195",
      "diretoria": "RD",
      "cliente": "ENERGISA MS",
      "contrato": "WS99091 - LESTE/SUL",
      "contratoCliente": "Nº WS 99091",
      "linhaNegocios": "LEITURA/STC",
      "mesReajuste": "Setembro",
      "clausula": "reajuste",
      "obs": "Página 2",
      "tipoContratacao": "Contrato Contínuo",
      "valorTotal": 156331193.94,
      "dataInicio": "2024-01-01",
      "dataTerminoAdtv": "2028-12-31",
      "vigenciaMeses": "59",
      "status": "ok",
      "indiceSugerido": "",
      "reajuste": ""
    },
    {
      "id": "114",
      "uen": "215",
      "diretoria": "RD",
      "cliente": "CEMIG",
      "contrato": "4680007176 - UEN 215",
      "contratoCliente": "4680007176",
      "linhaNegocios": "LEITURA",
      "mesReajuste": "Novembro",
      "clausula": "CLÁUSULA 6 - DO REAJUSTE",
      "obs": "",
      "tipoContratacao": "Contrato Contínuo",
      "valorTotal": 66033097.25,
      "dataInicio": "2024-06-01",
      "dataTerminoAdtv": "2029-06-01",
      "vigenciaMeses": "60",
      "status": "ok",
      "indiceSugerido": "",
      "reajuste": ""
    },
    {
      "id": "117",
      "uen": "668",
      "diretoria": "GT",
      "cliente": "EDP T",
      "contrato": "5600004663 - UEN 668",
      "contratoCliente": "5600004663",
      "linhaNegocios": "MANUTENÇÃO",
      "mesReajuste": "Fevereiro",
      "clausula": "5",
      "obs": "",
      "tipoContratacao": "Contrato Contínuo",
      "valorTotal": 5046134.28,
      "dataInicio": "2024-03-18",
      "dataTerminoAdtv": "2027-03-18",
      "vigenciaMeses": "36",
      "status": "ok",
      "indiceSugerido": "",
      "reajuste": "P = PO + PO x (40% x MO + 10% x ME + 5% x DI + 45% x IPCA).\n\nPO = Preço data base – Data base: assinatura do contrato;\nMO = Mão de obra – INCC – DI = código 160906, FGV;\nME = IPA-EP-DI Máquinas, aparelhos e equipamentos – código 1416650, FGV\nDI = Diesel S-10 = Variação preço médio revenda, Centro Oeste, ANP (https://www.gov.br/anp/pt-br/assuntos/precos-e-defesa-da-concorrencia/precos/precos-revenda-e-de-distribuicao-combustiveis/serie-historica-do-levantamento-de-precos);\nIPCA = Índice Nacional de Preços ao Consumidor Amplo."
    },
    {
      "id": "118",
      "uen": "196",
      "diretoria": "RD",
      "cliente": "ENERGISA MS",
      "contrato": "WS100002 - UEN 196",
      "contratoCliente": "WS 100.002",
      "linhaNegocios": "STC",
      "mesReajuste": "Fevereiro",
      "clausula": "REAJUSTE",
      "obs": "",
      "tipoContratacao": "Contrato Contínuo",
      "valorTotal": 11289071.96,
      "dataInicio": "2024-03-01",
      "dataTerminoAdtv": "2028-02-29",
      "vigenciaMeses": "47",
      "status": "ok",
      "indiceSugerido": "ipca_12m",
      "reajuste": "IPCA"
    },
    {
      "id": "119",
      "uen": "809",
      "diretoria": "GT",
      "cliente": "PONTAL ENERGY",
      "contrato": "2024 03 01- UEN 809",
      "contratoCliente": "2024-03-01-CPS-ECA-ECD",
      "linhaNegocios": "O&M",
      "mesReajuste": "",
      "clausula": "",
      "obs": "",
      "tipoContratacao": "Contrato Contínuo",
      "valorTotal": 0,
      "dataInicio": "2024-03-01",
      "dataTerminoAdtv": "2026-03-01",
      "vigenciaMeses": "24",
      "status": "atrasado",
      "indiceSugerido": "",
      "reajuste": ""
    },
    {
      "id": "121",
      "uen": "902",
      "diretoria": "GT",
      "cliente": "ANGLO AMERICAN",
      "contrato": "4600036723 - UEN 902",
      "contratoCliente": "4600036723",
      "linhaNegocios": "INDÚSTRIA",
      "mesReajuste": "",
      "clausula": "",
      "obs": "",
      "tipoContratacao": "Execução de Projeto",
      "valorTotal": 7632000.0,
      "dataInicio": "2024-03-28",
      "dataTerminoAdtv": "2026-06-30",
      "vigenciaMeses": "27",
      "status": "ok",
      "indiceSugerido": "ipca_12m",
      "reajuste": "IPCA"
    },
    {
      "id": "122",
      "uen": "670",
      "diretoria": "GT",
      "cliente": "CTEEP",
      "contrato": "4600008708 - UEN 670",
      "contratoCliente": "4600008708",
      "linhaNegocios": "MANUTENÇÃO",
      "mesReajuste": "Abril",
      "clausula": "3.5.1",
      "obs": "",
      "tipoContratacao": "Contrato Contínuo",
      "valorTotal": 8955361.59,
      "dataInicio": "2024-04-11",
      "dataTerminoAdtv": "2027-04-11",
      "vigenciaMeses": "36",
      "status": "ok",
      "indiceSugerido": "",
      "reajuste": "Índice do reajuste: Os preços unitários poderão ser \nreajustados 12 (doze) meses da data de início do Contrato, \nconforme composição abaixo:  \na) 70% (setenta por cento) do dissídio da categoria \n(Sindicato): SINTRACOM SUDOESTE; e  \nb) 30% (trinta por cento) do Índice Nacional de Preços ao \nConsumidor Amplo - IPCA."
    },
    {
      "id": "123",
      "uen": "620",
      "diretoria": "GT",
      "cliente": "ATLANCTIC NICKEL",
      "contrato": "4375 - UEN 620",
      "contratoCliente": "4375",
      "linhaNegocios": "MANUTENÇÃO",
      "mesReajuste": "Abril",
      "clausula": "5.1(e)",
      "obs": "",
      "tipoContratacao": "Contrato Contínuo",
      "valorTotal": 1024929.0,
      "dataInicio": "2024-04-22",
      "dataTerminoAdtv": "2026-06-22",
      "vigenciaMeses": "26",
      "status": "ok",
      "indiceSugerido": "",
      "reajuste": ""
    },
    {
      "id": "126",
      "uen": "826",
      "diretoria": "GT",
      "cliente": "MATRIX",
      "contrato": "S/N - UEN 826",
      "contratoCliente": "S/N - UEN 826",
      "linhaNegocios": "O&M",
      "mesReajuste": "Maio",
      "clausula": "",
      "obs": "",
      "tipoContratacao": "Contrato Contínuo",
      "valorTotal": 2334936.0,
      "dataInicio": "2024-06-15",
      "dataTerminoAdtv": "2026-06-15",
      "vigenciaMeses": "24",
      "status": "ok",
      "indiceSugerido": "ipca_12m",
      "reajuste": "IPCA"
    },
    {
      "id": "127",
      "uen": "106, 107",
      "diretoria": "RD",
      "cliente": "EDP ES",
      "contrato": "5600005071 - 106/107",
      "contratoCliente": "5600005071",
      "linhaNegocios": "LEITURA",
      "mesReajuste": "Julho",
      "clausula": "3.4",
      "obs": "",
      "tipoContratacao": "Contrato Contínuo",
      "valorTotal": 54674596.23,
      "dataInicio": "2024-08-01",
      "dataTerminoAdtv": "2027-08-01",
      "vigenciaMeses": "36",
      "status": "ok",
      "indiceSugerido": "",
      "reajuste": ""
    },
    {
      "id": "130",
      "uen": "647, 648, 649",
      "diretoria": "GT",
      "cliente": "EQUATORIAL",
      "contrato": "00249/2024-EQUATORIA",
      "contratoCliente": "00249/2024",
      "linhaNegocios": "MANUTENÇÃO",
      "mesReajuste": "Maio",
      "clausula": "4ª - Parágrafo Terceiro",
      "obs": "",
      "tipoContratacao": "Contrato Contínuo",
      "valorTotal": 29320802.0,
      "dataInicio": "2024-05-31",
      "dataTerminoAdtv": "2027-05-31",
      "vigenciaMeses": "36",
      "status": "ok",
      "indiceSugerido": "",
      "reajuste": "P = PO + PO x (40% x MO + 10% x ME + 5% x DI + 45% x IPCA).\n\nPO = Preço data base – Data base: assinatura do contrato;\nMO = Mão de obra – INCC – DI = código 160906, FGV;\nME = IPA-EP-DI Máquinas, aparelhos e equipamentos – código 1416650, FGV\nDI = Diesel S-10 = Variação preço médio revenda, Centro Oeste, ANP (https://www.gov.br/anp/pt-br/assuntos/precos-e-defesa-da-concorrencia/precos/precos-revenda-e-de-distribuicao-combustiveis/serie-historica-do-levantamento-de-precos);\nIPCA = Índice Nacional de Preços ao Consumidor Amplo."
    },
    {
      "id": "131",
      "uen": "199",
      "diretoria": "RD",
      "cliente": "EMT",
      "contrato": "WS 101102 - UEN 199",
      "contratoCliente": "101102",
      "linhaNegocios": "STC",
      "mesReajuste": "",
      "clausula": "",
      "obs": "Não terá reajuste, visto que o contrato é 12 meses",
      "tipoContratacao": "Contrato Contínuo",
      "valorTotal": 35019844.2,
      "dataInicio": "2024-07-01",
      "dataTerminoAdtv": "2026-12-31",
      "vigenciaMeses": "29",
      "status": "ok",
      "indiceSugerido": "",
      "reajuste": ""
    },
    {
      "id": "133",
      "uen": "280",
      "diretoria": "RD",
      "cliente": "ENERGISA MS",
      "contrato": "WS 101284 - UEN 280",
      "contratoCliente": "WS 101284",
      "linhaNegocios": "CCM",
      "mesReajuste": "Junho",
      "clausula": "REAJUSTE",
      "obs": "",
      "tipoContratacao": "Contrato Contínuo",
      "valorTotal": 32895689.75,
      "dataInicio": "2024-06-17",
      "dataTerminoAdtv": "2029-06-16",
      "vigenciaMeses": "59",
      "status": "ok",
      "indiceSugerido": "ipca_12m",
      "reajuste": "IPCA"
    },
    {
      "id": "134",
      "uen": "827",
      "diretoria": "GT",
      "cliente": "MATRIX",
      "contrato": "S/N - UEN 827",
      "contratoCliente": "S/N - UEN 827",
      "linhaNegocios": "O&M",
      "mesReajuste": "Abril",
      "clausula": "Proposta",
      "obs": "",
      "tipoContratacao": "Contrato Contínuo",
      "valorTotal": 1379856.0,
      "dataInicio": "2024-09-02",
      "dataTerminoAdtv": "2026-09-02",
      "vigenciaMeses": "24",
      "status": "ok",
      "indiceSugerido": "",
      "reajuste": "I = 1 + (0,66 INPC + 0,10 CL + 0,24 E)"
    },
    {
      "id": "135",
      "uen": "211",
      "diretoria": "RD",
      "cliente": "CEMIG",
      "contrato": "4680007360 - UEN 211",
      "contratoCliente": "4680007360",
      "linhaNegocios": "STC",
      "mesReajuste": "Junho",
      "clausula": "CLÁUSULA 6 - DO REAJUSTE",
      "obs": "",
      "tipoContratacao": "Contrato Contínuo",
      "valorTotal": 185060839.47,
      "dataInicio": "2024-10-15",
      "dataTerminoAdtv": "2029-10-15",
      "vigenciaMeses": "60",
      "status": "ok",
      "indiceSugerido": "",
      "reajuste": ""
    },
    {
      "id": "137",
      "uen": "904",
      "diretoria": "GT",
      "cliente": "CSN",
      "contrato": "CW2336778 - UEN 904",
      "contratoCliente": "CW2336778",
      "linhaNegocios": "INDÚSTRIA",
      "mesReajuste": "Agosto",
      "clausula": "Anexo II",
      "obs": "",
      "tipoContratacao": "Contrato Contínuo",
      "valorTotal": 3895335.0,
      "dataInicio": "2024-08-01",
      "dataTerminoAdtv": "2027-08-01",
      "vigenciaMeses": "36",
      "status": "ok",
      "indiceSugerido": "ipca_12m",
      "reajuste": "IPCA"
    },
    {
      "id": "138",
      "uen": "828",
      "diretoria": "GT",
      "cliente": "CASA DOS VENTOS",
      "contrato": "4600201947 - UEN 828",
      "contratoCliente": "4600201947",
      "linhaNegocios": "O&M",
      "mesReajuste": "Julho",
      "clausula": "4.3",
      "obs": "",
      "tipoContratacao": "Contrato Contínuo",
      "valorTotal": 0,
      "dataInicio": "2024-07-30",
      "dataTerminoAdtv": "2026-07-30",
      "vigenciaMeses": "24",
      "status": "ok",
      "indiceSugerido": "ipca_12m",
      "reajuste": "IPCA"
    },
    {
      "id": "139",
      "uen": "828",
      "diretoria": "GT",
      "cliente": "CASA DOS VENTOS",
      "contrato": "4600201948 - UEN 828",
      "contratoCliente": "4600201948",
      "linhaNegocios": "O&M",
      "mesReajuste": "Julho",
      "clausula": "4.3",
      "obs": "",
      "tipoContratacao": "Contrato Contínuo",
      "valorTotal": 0,
      "dataInicio": "2024-07-30",
      "dataTerminoAdtv": "2026-07-30",
      "vigenciaMeses": "24",
      "status": "ok",
      "indiceSugerido": "ipca_12m",
      "reajuste": "IPCA"
    },
    {
      "id": "141",
      "uen": "672",
      "diretoria": "GT",
      "cliente": "SANTO ANTONIO ENERGIA",
      "contrato": "CT.GMA.024.2024 -672",
      "contratoCliente": "CT.GMA.024.2024",
      "linhaNegocios": "MANUTENÇÃO",
      "mesReajuste": "Outubro",
      "clausula": "4.3",
      "obs": "",
      "tipoContratacao": "Contrato Contínuo",
      "valorTotal": 4896637.0,
      "dataInicio": "2024-10-28",
      "dataTerminoAdtv": "2027-10-28",
      "vigenciaMeses": "36",
      "status": "ok",
      "indiceSugerido": "",
      "reajuste": ""
    },
    {
      "id": "143",
      "uen": "153",
      "diretoria": "RD",
      "cliente": "ENEL SP",
      "contrato": "4600004059 - UEN 153",
      "contratoCliente": "4600004059 / JA10163565",
      "linhaNegocios": "CCM",
      "mesReajuste": "Outubro",
      "clausula": "5.8",
      "obs": "",
      "tipoContratacao": "Contrato Contínuo",
      "valorTotal": 27000000.0,
      "dataInicio": "2024-10-30",
      "dataTerminoAdtv": "2026-04-30",
      "vigenciaMeses": "18",
      "status": "vence",
      "indiceSugerido": "",
      "reajuste": ""
    },
    {
      "id": "145",
      "uen": "831",
      "diretoria": "GT",
      "cliente": "CGN",
      "contrato": "SOL 5398 - UEN 831",
      "contratoCliente": "SOL 5398 Guarda-Chuva",
      "linhaNegocios": "O&M",
      "mesReajuste": "Novembro",
      "clausula": "5",
      "obs": "",
      "tipoContratacao": "Contrato Contínuo",
      "valorTotal": 385932.59,
      "dataInicio": "2024-11-30",
      "dataTerminoAdtv": "2028-02-10",
      "vigenciaMeses": "38",
      "status": "ok",
      "indiceSugerido": "ipca_12m",
      "reajuste": "IPCA"
    },
    {
      "id": "146",
      "uen": "832",
      "diretoria": "GT",
      "cliente": "ENGIE",
      "contrato": "RRBA.DPS.24.3156-832",
      "contratoCliente": "RRBA.DPS.24.3156",
      "linhaNegocios": "O&M",
      "mesReajuste": "Janeiro",
      "clausula": "CLÁUSULA DÉCIMA PRIMEIRA",
      "obs": "",
      "tipoContratacao": "Contrato Contínuo",
      "valorTotal": 1722230.21,
      "dataInicio": "2025-01-01",
      "dataTerminoAdtv": "2027-06-30",
      "vigenciaMeses": "29",
      "status": "ok",
      "indiceSugerido": "ipca_12m",
      "reajuste": "IPCA"
    },
    {
      "id": "147",
      "uen": "678",
      "diretoria": "GT",
      "cliente": "ELETROBRAS",
      "contrato": "8000013932 - UEN 678",
      "contratoCliente": "8000013932",
      "linhaNegocios": "MANUTENÇÃO",
      "mesReajuste": "Dezembro",
      "clausula": "3.2",
      "obs": "Página 4",
      "tipoContratacao": "Contrato Contínuo",
      "valorTotal": 7107489.5,
      "dataInicio": "2024-12-26",
      "dataTerminoAdtv": "2026-12-26",
      "vigenciaMeses": "24",
      "status": "ok",
      "indiceSugerido": "ipca_12m",
      "reajuste": "IPCA"
    },
    {
      "id": "148",
      "uen": "650",
      "diretoria": "GT",
      "cliente": "VERENE",
      "contrato": "00249/2024 - UEN 650",
      "contratoCliente": "00249/2024",
      "linhaNegocios": "MANUTENÇÃO",
      "mesReajuste": "Maio",
      "clausula": "4ª - Parágrafo Terceiro",
      "obs": "",
      "tipoContratacao": "Contrato Contínuo",
      "valorTotal": 2593080.0,
      "dataInicio": "2024-09-12",
      "dataTerminoAdtv": "2027-05-31",
      "vigenciaMeses": "32",
      "status": "ok",
      "indiceSugerido": "ipca_12m",
      "reajuste": "IPCA"
    },
    {
      "id": "149",
      "uen": "674,675,676",
      "diretoria": "RD",
      "cliente": "ENEL RIO",
      "contrato": "JA10166038-AT NORTE",
      "contratoCliente": "JA10166038\nBR0078291047",
      "linhaNegocios": "ALTA TENSÃO",
      "mesReajuste": "Janeiro",
      "clausula": "5.7",
      "obs": "",
      "tipoContratacao": "Contrato Contínuo",
      "valorTotal": 113923303.13,
      "dataInicio": "2025-01-15",
      "dataTerminoAdtv": "2028-01-15",
      "vigenciaMeses": "36",
      "status": "ok",
      "indiceSugerido": "inpc_12m",
      "reajuste": "INPC"
    },
    {
      "id": "150",
      "uen": "301",
      "diretoria": "RD",
      "cliente": "COPEL",
      "contrato": "4600029608 - UEN 301",
      "contratoCliente": "4600029608/2025",
      "linhaNegocios": "LEITURA",
      "mesReajuste": "Novembro",
      "clausula": "CLÁUSULA VIII. REAJUSTE DE PREÇOS",
      "obs": "",
      "tipoContratacao": "Contrato Contínuo",
      "valorTotal": 85132540.01,
      "dataInicio": "2025-03-23",
      "dataTerminoAdtv": "2028-03-23",
      "vigenciaMeses": "36",
      "status": "ok",
      "indiceSugerido": "ipca_12m",
      "reajuste": "IPCA"
    },
    {
      "id": "151",
      "uen": "658",
      "diretoria": "GT",
      "cliente": "CPFL R",
      "contrato": "4600089888 - UEN 658",
      "contratoCliente": "4600089888",
      "linhaNegocios": "MANUTENÇÃO",
      "mesReajuste": "Março",
      "clausula": "6.1.2",
      "obs": "",
      "tipoContratacao": "Contrato Contínuo",
      "valorTotal": 12199083.7,
      "dataInicio": "2025-03-21",
      "dataTerminoAdtv": "2028-03-21",
      "vigenciaMeses": "36",
      "status": "ok",
      "indiceSugerido": "ipca_12m",
      "reajuste": "IPCA"
    },
    {
      "id": "153",
      "uen": "264, 265, 266",
      "diretoria": "RD",
      "cliente": "ENEL RIO",
      "contrato": "JA10170087 - MARICA",
      "contratoCliente": "JA10170087",
      "linhaNegocios": "CCM",
      "mesReajuste": "Abril",
      "clausula": "5.9",
      "obs": "",
      "tipoContratacao": "Contrato Contínuo",
      "valorTotal": 80538834.78,
      "dataInicio": "2025-04-01",
      "dataTerminoAdtv": "2028-04-01",
      "vigenciaMeses": "36",
      "status": "ok",
      "indiceSugerido": "",
      "reajuste": "55% do IPCA-IBGE e 45% do INPC"
    },
    {
      "id": "154",
      "uen": "253, 254, 255, 256, 257, 258, 259, 260, 261, 262, 263",
      "diretoria": "RD",
      "cliente": "ENEL RIO",
      "contrato": "JA10171327 - LAGOS",
      "contratoCliente": "JA10171327",
      "linhaNegocios": "CCM/STC",
      "mesReajuste": "Março",
      "clausula": "5.9",
      "obs": "",
      "tipoContratacao": "Contrato Contínuo",
      "valorTotal": 384254017.58,
      "dataInicio": "2025-04-17",
      "dataTerminoAdtv": "2028-04-17",
      "vigenciaMeses": "36",
      "status": "ok",
      "indiceSugerido": "ipca_12m",
      "reajuste": "IPCA"
    },
    {
      "id": "155",
      "uen": "830",
      "diretoria": "GT",
      "cliente": "ENEVA",
      "contrato": "4600003470 - UEN 830",
      "contratoCliente": "4600003470",
      "linhaNegocios": "O&M",
      "mesReajuste": "Março",
      "clausula": "5.2",
      "obs": "",
      "tipoContratacao": "Contrato Contínuo",
      "valorTotal": 2403864.0,
      "dataInicio": "2025-03-13",
      "dataTerminoAdtv": "2028-03-13",
      "vigenciaMeses": "36",
      "status": "ok",
      "indiceSugerido": "",
      "reajuste": "73,75% INPC + 20,75% COMBUSTÍVEIS + 5,5% INFRA E MATERIAIS, VEÍCULOS, MANUTENÇÃO E PEÇAS"
    },
    {
      "id": "156",
      "uen": "330",
      "diretoria": "RD",
      "cliente": "EDP SP",
      "contrato": "5600006070 - UEN 330",
      "contratoCliente": "5600006070",
      "linhaNegocios": "STC",
      "mesReajuste": "Janeiro",
      "clausula": "4.5",
      "obs": "",
      "tipoContratacao": "Contrato Contínuo",
      "valorTotal": 109817355.55,
      "dataInicio": "2025-07-01",
      "dataTerminoAdtv": "2030-07-01",
      "vigenciaMeses": "60",
      "status": "ok",
      "indiceSugerido": "",
      "reajuste": "73,75% INPC + 20,75% COMBUSTÍVEIS + 5,5% INFRA E MATERIAIS, VEÍCULOS, MANUTENÇÃO E PEÇAS"
    },
    {
      "id": "157",
      "uen": "331",
      "diretoria": "RD",
      "cliente": "EDP SP",
      "contrato": "5600006069 - UEN 331",
      "contratoCliente": "5600006069",
      "linhaNegocios": "CCM",
      "mesReajuste": "Janeiro",
      "clausula": "4.5",
      "obs": "",
      "tipoContratacao": "Contrato Contínuo",
      "valorTotal": 146096584.43,
      "dataInicio": "2025-07-01",
      "dataTerminoAdtv": "2030-07-01",
      "vigenciaMeses": "60",
      "status": "ok",
      "indiceSugerido": "ipca_12m",
      "reajuste": "IPCA"
    },
    {
      "id": "158",
      "uen": "833",
      "diretoria": "GT",
      "cliente": "PONTAL ENERGY",
      "contrato": "S/N UEN 833",
      "contratoCliente": "S/N UEN 833",
      "linhaNegocios": "O&M",
      "mesReajuste": "Abril",
      "clausula": "Anexo I - B",
      "obs": "",
      "tipoContratacao": "Contrato Contínuo",
      "valorTotal": 0,
      "dataInicio": "2025-04-28",
      "dataTerminoAdtv": "2028-04-28",
      "vigenciaMeses": "36",
      "status": "ok",
      "indiceSugerido": "",
      "reajuste": ""
    },
    {
      "id": "160",
      "uen": "679",
      "diretoria": "GT",
      "cliente": "EDP T",
      "contrato": "5600006201 - UEN 679",
      "contratoCliente": "5600006201",
      "linhaNegocios": "O&M",
      "mesReajuste": "Maio",
      "clausula": "3.2",
      "obs": "",
      "tipoContratacao": "Contrato Contínuo",
      "valorTotal": 7875084.0,
      "dataInicio": "2025-05-16",
      "dataTerminoAdtv": "2026-05-16",
      "vigenciaMeses": "12",
      "status": "ok",
      "indiceSugerido": "ipca_12m",
      "reajuste": "IPCA"
    },
    {
      "id": "161",
      "uen": "611",
      "diretoria": "GT",
      "cliente": "BRASKEM",
      "contrato": "4600031309 - UEN 611",
      "contratoCliente": "4600031309",
      "linhaNegocios": "INDÚSTRIA",
      "mesReajuste": "Abril",
      "clausula": "F.2.2)",
      "obs": "",
      "tipoContratacao": "Contrato Contínuo",
      "valorTotal": 8107674.66,
      "dataInicio": "2025-05-26",
      "dataTerminoAdtv": "2029-05-26",
      "vigenciaMeses": "48",
      "status": "ok",
      "indiceSugerido": "ipca_12m",
      "reajuste": "IPCA"
    },
    {
      "id": "163",
      "uen": "834",
      "diretoria": "GT",
      "cliente": "SOLARIG",
      "contrato": "00027 - UEN 834",
      "contratoCliente": "00027",
      "linhaNegocios": "O&M",
      "mesReajuste": "Abril",
      "clausula": "Proposta Comercial - Item 9. PREÇOS - III",
      "obs": "",
      "tipoContratacao": "Contrato Contínuo",
      "valorTotal": 4275390.0,
      "dataInicio": "2025-05-05",
      "dataTerminoAdtv": "2030-05-05",
      "vigenciaMeses": "60",
      "status": "ok",
      "indiceSugerido": "ipca_12m",
      "reajuste": "IPCA"
    },
    {
      "id": "164",
      "uen": "771",
      "diretoria": "GT",
      "cliente": "EDP T",
      "contrato": "5600006378 - UEN 771",
      "contratoCliente": "5600006378",
      "linhaNegocios": "CONSTRUÇÃO",
      "mesReajuste": "Agosto",
      "clausula": "3.2",
      "obs": "IPCA",
      "tipoContratacao": "Execução de Projeto",
      "valorTotal": 30900074.59,
      "dataInicio": "2025-08-08",
      "dataTerminoAdtv": "2026-08-08",
      "vigenciaMeses": "12",
      "status": "ok",
      "indiceSugerido": "",
      "reajuste": ""
    },
    {
      "id": "165",
      "uen": "829",
      "diretoria": "GT",
      "cliente": "RENOVA",
      "contrato": "OMEOL202500018 - 829",
      "contratoCliente": "OMEOL202500018",
      "linhaNegocios": "O&M",
      "mesReajuste": "",
      "clausula": "",
      "obs": "",
      "tipoContratacao": "Execução de Projeto",
      "valorTotal": 479520.0,
      "dataInicio": "2025-08-15",
      "dataTerminoAdtv": "2026-02-28",
      "vigenciaMeses": "6",
      "status": "atrasado",
      "indiceSugerido": "",
      "reajuste": ""
    },
    {
      "id": "166",
      "uen": "811",
      "diretoria": "GT",
      "cliente": "SAMARCO",
      "contrato": "4600004329 - UEN 811",
      "contratoCliente": "4600004329",
      "linhaNegocios": "O&M",
      "mesReajuste": "",
      "clausula": "",
      "obs": "",
      "tipoContratacao": "Execução de Projeto",
      "valorTotal": 495611.88,
      "dataInicio": "2025-07-14",
      "dataTerminoAdtv": "2026-01-14",
      "vigenciaMeses": "6",
      "status": "atrasado",
      "indiceSugerido": "",
      "reajuste": "fórmula paramétrica de 55% (cinquenta e cinco por cento) da variação do IPCA-IBGE e 45%\n(quarenta e cinco por cento) da variação do INPC"
    },
    {
      "id": "167",
      "uen": "270, 272",
      "diretoria": "RD",
      "cliente": "ENEL RIO",
      "contrato": "JA10178257 - SOT NOR",
      "contratoCliente": "JA10178257",
      "linhaNegocios": "CCM",
      "mesReajuste": "Julho",
      "clausula": "5.9",
      "obs": "",
      "tipoContratacao": "Contrato Contínuo",
      "valorTotal": 120522955.72,
      "dataInicio": "2025-08-27",
      "dataTerminoAdtv": "2028-08-27",
      "vigenciaMeses": "36",
      "status": "ok",
      "indiceSugerido": "",
      "reajuste": "fórmula paramétrica de 55% (cinquenta e cinco por cento) da variação do IPCA-IBGE e 45%\n(quarenta e cinco por cento) da variação do INPC"
    },
    {
      "id": "168",
      "uen": "268, 269, 271",
      "diretoria": "RD",
      "cliente": "ENEL RIO",
      "contrato": "JA10178258 - SOC NOR",
      "contratoCliente": "JA10178258",
      "linhaNegocios": "STC",
      "mesReajuste": "Julho",
      "clausula": "5.9",
      "obs": "",
      "tipoContratacao": "Contrato Contínuo",
      "valorTotal": 81862012.42,
      "dataInicio": "2025-08-27",
      "dataTerminoAdtv": "2028-08-27",
      "vigenciaMeses": "36",
      "status": "ok",
      "indiceSugerido": "",
      "reajuste": "fórmula paramétrica de 55% (cinquenta e cinco por cento) da variação do IPCA-IBGE e 45%\n(quarenta e cinco por cento) da variação do INPC"
    },
    {
      "id": "169",
      "uen": "INATIVA",
      "diretoria": "RD",
      "cliente": "ENEL RIO",
      "contrato": "JA10178259 - MERC NO",
      "contratoCliente": "JA10178259",
      "linhaNegocios": "STC",
      "mesReajuste": "Julho",
      "clausula": "5.9",
      "obs": "",
      "tipoContratacao": "Contrato Contínuo",
      "valorTotal": 42804755.95,
      "dataInicio": "2025-08-27",
      "dataTerminoAdtv": "2028-08-27",
      "vigenciaMeses": "36",
      "status": "ok",
      "indiceSugerido": "",
      "reajuste": ""
    },
    {
      "id": "171",
      "uen": "772",
      "diretoria": "GT",
      "cliente": "ARCELORMITTAL",
      "contrato": "5800042154 - UEN 772",
      "contratoCliente": "5800042154",
      "linhaNegocios": "CONSTRUÇÃO",
      "mesReajuste": "Setembro",
      "clausula": "",
      "obs": "Não Tem Cláusula de Reajuste",
      "tipoContratacao": "Execução de Projeto",
      "valorTotal": 4196035.0,
      "dataInicio": "2025-09-15",
      "dataTerminoAdtv": "2027-03-15",
      "vigenciaMeses": "18",
      "status": "ok",
      "indiceSugerido": "",
      "reajuste": "fórmula paramétrica de 55% (cinquenta e cinco por cento) da variação do IPCA-IBGE e 45%\n(quarenta e cinco por cento) da variação do INPC"
    },
    {
      "id": "172",
      "uen": "273",
      "diretoria": "RD",
      "cliente": "ENEL RIO",
      "contrato": "JA10179594 - SOC RES",
      "contratoCliente": "JA10179594",
      "linhaNegocios": "STC",
      "mesReajuste": "Outubro",
      "clausula": "5.9",
      "obs": "",
      "tipoContratacao": "Contrato Contínuo",
      "valorTotal": 34092225.88,
      "dataInicio": "2025-10-01",
      "dataTerminoAdtv": "2028-10-01",
      "vigenciaMeses": "36",
      "status": "ok",
      "indiceSugerido": "",
      "reajuste": "fórmula paramétrica de 55% (cinquenta e cinco por cento) da variação do IPCA-IBGE e 45%\n(quarenta e cinco por cento) da variação do INPC"
    },
    {
      "id": "173",
      "uen": "274, 275",
      "diretoria": "RD",
      "cliente": "ENEL RIO",
      "contrato": "JA10179596 - SOT RES",
      "contratoCliente": "JA10179596",
      "linhaNegocios": "CCM",
      "mesReajuste": "Outubro",
      "clausula": "5.9",
      "obs": "",
      "tipoContratacao": "Contrato Contínuo",
      "valorTotal": 69309328.0,
      "dataInicio": "2025-10-01",
      "dataTerminoAdtv": "2028-10-01",
      "vigenciaMeses": "36",
      "status": "ok",
      "indiceSugerido": "",
      "reajuste": "fórmula paramétrica de 55% (cinquenta e cinco por cento) da variação do IPCA-IBGE e 45%\n(quarenta e cinco por cento) da variação do INPC"
    },
    {
      "id": "175",
      "uen": "773",
      "diretoria": "GT",
      "cliente": "EDP ES",
      "contrato": "5600006475 - UEN 773",
      "contratoCliente": "5600006475",
      "linhaNegocios": "CONSTRUÇÃO",
      "mesReajuste": "",
      "clausula": "",
      "obs": "",
      "tipoContratacao": "Execução de Projeto",
      "valorTotal": 4295605.65,
      "dataInicio": "2025-09-30",
      "dataTerminoAdtv": "2026-05-30",
      "vigenciaMeses": "8",
      "status": "ok",
      "indiceSugerido": "incc",
      "reajuste": "INCC"
    },
    {
      "id": "176",
      "uen": "902",
      "diretoria": "GT",
      "cliente": "ANGLO AMERICAN",
      "contrato": "4600045482 - UEN 902",
      "contratoCliente": "4600045482",
      "linhaNegocios": "INDÚSTRIA",
      "mesReajuste": "Setembro",
      "clausula": "6.7",
      "obs": "",
      "tipoContratacao": "Execução de Projeto",
      "valorTotal": 1780074.0,
      "dataInicio": "2025-10-08",
      "dataTerminoAdtv": "2026-10-08",
      "vigenciaMeses": "12",
      "status": "ok",
      "indiceSugerido": "ipca_12m",
      "reajuste": "IPCA"
    },
    {
      "id": "177",
      "uen": "681",
      "diretoria": "GT",
      "cliente": "VERENE",
      "contrato": "197.2025 - UEN 681",
      "contratoCliente": "197.2025",
      "linhaNegocios": "MANUTENÇÃO",
      "mesReajuste": "Outubro",
      "clausula": "8.9",
      "obs": "",
      "tipoContratacao": "Contrato Contínuo",
      "valorTotal": 13450000.0,
      "dataInicio": "2025-10-30",
      "dataTerminoAdtv": "2029-12-30",
      "vigenciaMeses": "50",
      "status": "ok",
      "indiceSugerido": "",
      "reajuste": "PR=P0*[0,45*(IPCA¹ / IPCAº) + 0,30*(IGP-DI¹ / IGP-DIº) + 0,25 *(INCC¹ / INCCº)]\nPR - Preço Reajustado\nP0 - Preço Atual\n0,45 - IPCA (1004963) - IBGE\n0,30 - IGP-DI (161384)\n0,25 - INCC-DI All Itens Col. 47A Stepwise (1464783)\nÍndice¹ - Índice FGV do mês anterior de aniversário da assinatura do contrato\nÍndiceº - Índice FGV do mês anterior à data de assinatura do contrato"
    },
    {
      "id": "178",
      "uen": "906",
      "diretoria": "GT",
      "cliente": "VALE",
      "contrato": "5500125727 - UEN 906",
      "contratoCliente": "5500125727",
      "linhaNegocios": "INDÚSTRIA",
      "mesReajuste": "Outubro",
      "clausula": "3.4",
      "obs": "",
      "tipoContratacao": "Contrato Contínuo",
      "valorTotal": 100773404.54,
      "dataInicio": "2025-10-31",
      "dataTerminoAdtv": "2028-12-23",
      "vigenciaMeses": "37",
      "status": "ok",
      "indiceSugerido": "ipca_12m",
      "reajuste": "IPCA"
    },
    {
      "id": "179",
      "uen": "267",
      "diretoria": "RD",
      "cliente": "LIGHT",
      "contrato": "S/N - UEN 267",
      "contratoCliente": "S/N",
      "linhaNegocios": "CCM",
      "mesReajuste": "Agosto",
      "clausula": "5.6",
      "obs": "",
      "tipoContratacao": "Contrato Contínuo",
      "valorTotal": 32369952.0,
      "dataInicio": "2025-11-14",
      "dataTerminoAdtv": "2028-02-14",
      "vigenciaMeses": "27",
      "status": "ok",
      "indiceSugerido": "",
      "reajuste": ""
    },
    {
      "id": "180",
      "uen": "774",
      "diretoria": "GT",
      "cliente": "IMETAME",
      "contrato": "000092 - UEN 774",
      "contratoCliente": "000092",
      "linhaNegocios": "CONSTRUÇÃO",
      "mesReajuste": "",
      "clausula": "",
      "obs": "",
      "tipoContratacao": "Execução de Projeto",
      "valorTotal": 2200000.0,
      "dataInicio": "2025-11-18",
      "dataTerminoAdtv": "2026-08-18",
      "vigenciaMeses": "9",
      "status": "ok",
      "indiceSugerido": "ipca_12m",
      "reajuste": "IPCA"
    },
    {
      "id": "181",
      "uen": "775",
      "diretoria": "GT",
      "cliente": "CPFL T",
      "contrato": "S/N - UEN 775",
      "contratoCliente": "S/N",
      "linhaNegocios": "CONSTRUÇÃO",
      "mesReajuste": "Outubro",
      "clausula": "17.1",
      "obs": "",
      "tipoContratacao": "Execução de Projeto",
      "valorTotal": 152758928.76,
      "dataInicio": "2025-10-31",
      "dataTerminoAdtv": "2029-10-28",
      "vigenciaMeses": "47",
      "status": "ok",
      "indiceSugerido": "ipca_12m",
      "reajuste": "IPCA"
    },
    {
      "id": "182",
      "uen": "682",
      "diretoria": "GT",
      "cliente": "NORTE ENERGIA",
      "contrato": "DOM-S-008/2025 - 682",
      "contratoCliente": "DOM-S-008/2025",
      "linhaNegocios": "MANUTENÇÃO",
      "mesReajuste": "Janeiro",
      "clausula": "6.9",
      "obs": "",
      "tipoContratacao": "Contrato Contínuo",
      "valorTotal": 11625060.0,
      "dataInicio": "2026-01-19",
      "dataTerminoAdtv": "2031-03-19",
      "vigenciaMeses": "62",
      "status": "ok",
      "indiceSugerido": "",
      "reajuste": "45% do IPCA + 30% do IGPD-I + 25% do INCC"
    },
    {
      "id": "183",
      "uen": "907",
      "diretoria": "GT",
      "cliente": "CSN",
      "contrato": "CW2374322 - UEN 907",
      "contratoCliente": "CW2374322",
      "linhaNegocios": "INDÚSTRIA",
      "mesReajuste": "Janeiro",
      "clausula": "11",
      "obs": "PAGINA 4",
      "tipoContratacao": "Execução de Projeto",
      "valorTotal": 16580904.52,
      "dataInicio": "2026-01-01",
      "dataTerminoAdtv": "2028-12-31",
      "vigenciaMeses": "35",
      "status": "ok",
      "indiceSugerido": "",
      "reajuste": "Fórmula paramétrica\nPr = Preço reajustado\nPv = Preço vigente\nINCC_MO = Índice Nacional de Custo da Construção, correspondente à mão-de-obra, publicado\npela revista Conjuntura Econômica da Fundação Getúlio Vargas, disponível no momento do cálculo\ndo reajuste.\nINCC_MOo = Índice Nacional de Custo da Construção, correspondente à mão-de-obra, publicado\npela revista Conjuntura Econômica da Fundação Getúlio Vargas, referente ao mês de assinatura do\ncontrato ou do último reajuste.\nINPC = Índice Nacional de Preços ao Consumidor, apurado pelo Instituto Brasileiro de Geografia e\nEstatística, disponível no momento do cálculo do reajuste.\nINPCo = Índice Nacional de Preços ao Consumidor, apurado pelo Instituto Brasileiro de Geografia\ne Estatística, referente ao mês de assinatura do contrato ou do último reajuste."
    },
    {
      "id": "184",
      "uen": "302",
      "diretoria": "RD",
      "cliente": "COPEL",
      "contrato": "847 - UEN 302",
      "contratoCliente": "847 |  4600031379",
      "linhaNegocios": "STC",
      "mesReajuste": "Fevereiro",
      "clausula": "VIII",
      "obs": "PAGINA 8",
      "tipoContratacao": "Contrato Contínuo",
      "valorTotal": 15777095.04,
      "dataInicio": "2026-02-03",
      "dataTerminoAdtv": "2028-02-03",
      "vigenciaMeses": "24",
      "status": "ok",
      "indiceSugerido": "",
      "reajuste": "CCM= 0,60 INCC (MO)+0,15 MEC +0,03 CL+ 0,22 IPCA"
    },
    {
      "id": "185",
      "uen": "216, 217",
      "diretoria": "RD",
      "cliente": "CEMIG",
      "contrato": "4680008095 - 216-217",
      "contratoCliente": "4680008095",
      "linhaNegocios": "CCM",
      "mesReajuste": "Fevereiro",
      "clausula": "6.1",
      "obs": "PÁGINA 13",
      "tipoContratacao": "Contrato Contínuo",
      "valorTotal": 284910597.0,
      "dataInicio": "2026-02-26",
      "dataTerminoAdtv": "2031-02-26",
      "vigenciaMeses": "60",
      "status": "ok",
      "indiceSugerido": "",
      "reajuste": ""
    }
  ]
}